MANIFEST.in
backend_shim.py
setup.py
integrate_ai_sdk/__init__.py
integrate_ai_sdk.egg-info/PKG-INFO
integrate_ai_sdk.egg-info/SOURCES.txt
integrate_ai_sdk.egg-info/dependency_links.txt
integrate_ai_sdk.egg-info/namespace_packages.txt
integrate_ai_sdk.egg-info/requires.txt
integrate_ai_sdk.egg-info/top_level.txt